metadsl_llvm/__init__.py
metadsl_llvm/ctypes.py
metadsl_llvm/integration.py
metadsl_llvm/integration_test.py
metadsl_llvm/ir.py
metadsl_llvm/ir_context.py
metadsl_llvm/ir_context_test.py
metadsl_llvm/ir_llvmlite.py
metadsl_llvm/llvmlite_binding.py
metadsl_llvm/strategies.py
metadsl_llvm-0.3.0.dist-info/WHEEL
metadsl_llvm-0.3.0.dist-info/METADATA
metadsl_llvm-0.3.0.dist-info/RECORD
